prog_client/__init__.py
prog_client/session.py
prog_server/__init__.py
prog_server/__main__.py
prog_server/app.py
prog_server/controllers.py
prog_server/models/__init__.py
prog_server/models/load_ests.py
prog_server/models/prediction_handler.py
prog_server/models/prog_server.py
prog_server/models/session.py
prog_server-1.7.0.dist-info/METADATA
prog_server-1.7.0.dist-info/WHEEL
prog_server-1.7.0.dist-info/top_level.txt
prog_server-1.7.0.dist-info/RECORD
