Metadata-Version: 2.1
Name: prog_server
Version: 1.7.0
Summary: The NASA Prognostics As-A-Service (PaaS) Sandbox (a.k.a. prog_server) is a simplified Software Oriented Architecture (SOA) for performing prognostics of engineering systems. The PaaS Sandbox is a wrapper around the Prognostics Algorithms and Models Packages, allowing 1+ users to access these packages features through a REST API. The package is intended to be used as a research tool to prototype and benchmark Prognostics As-A-Service (PaaS) architectures and work on the challenges facing
Home-page: https://nasa.github.com/progpy/prog_server_guide.html
Author: Christopher Teubert
Author-email: christopher.a.teubert@nasa.gov
License: NOSA
Project-URL: Bug Reports, https://github.com/nasa/prog_server/issues
Project-URL: Docs, https://nasa.github.io/progpy/prog_server_guide.html
Project-URL: Organization, https://www.nasa.gov/content/diagnostics-prognostics
Project-URL: Source, https://github.com/nasa/prog_server
Keywords: prognostics,diagnostics,fault detection,fdir,physics modeling,prognostics and health management,PHM,health management,prognostics as a service,ivhm
Classifier: Development Status :: 4 - Beta
Classifier: Intended Audience :: Science/Research
Classifier: Intended Audience :: Developers
Classifier: Intended Audience :: Manufacturing
Classifier: Topic :: Scientific/Engineering
Classifier: Topic :: Scientific/Engineering :: Artificial Intelligence
Classifier: Topic :: Scientific/Engineering :: Physics
Classifier: License :: Other/Proprietary License 
Classifier: Programming Language :: Python :: 3
Classifier: Programming Language :: Python :: 3.7
Classifier: Programming Language :: Python :: 3.8
Classifier: Programming Language :: Python :: 3.9
Classifier: Programming Language :: Python :: 3.10
Classifier: Programming Language :: Python :: 3.11
Classifier: Programming Language :: Python :: 3.12
Classifier: Programming Language :: Python :: 3 :: Only
Requires-Python: >=3.7, <3.13
Requires-Dist: progpy
Requires-Dist: requests
Requires-Dist: urllib3
Requires-Dist: flask
